{
    "interactionModel": {
        "languageModel": {
            "invocationName": "my mood",
            "intents": [
                {
                    "name": "AMAZON.CancelIntent",
                    "samples": [
                        "cancel"
                    ]
                },
                {
                    "name": "AMAZON.HelpIntent",
                    "samples": [
                        "how to use",
                        "manual"
                    ]
                },
                {
                    "name": "AMAZON.StopIntent",
                    "samples": [
                        "stop"
                    ]
                },
                {
                    "name": "AssessmentIntent",
                    "slots": [],
                    "samples": [
                        "Take an assessment",
                        "Quiz me.",
                        "I want to take a quiz.",
                        "I want to assess my mood.",
                        "Assess Me"
                    ]
                },
                {
                    "name": "ProfessionalHelpIntent",
                    "slots": [],
                    "samples": [
                        "look for professional help",
                        "find nearby help",
                        "Find a nearby clinic",
                        "Find professional help",
                        "Find help.",
                        "Help me.",
                        "Get help.",
                        "Find nearby help.",
                        "Where can I find help",
                        "Where can I get help.",
                        "I need help"
                    ]
                },
                {
                    "name": "AMAZON.RepeatIntent",
                    "samples": [
                        "say that again",
                        "repeat that"
                    ]
                },
                {
                    "name": "SentimentIntent",
                    "slots": [
                        {
                            "name": "phrase",
                            "type": "AMAZON.SearchQuery"
                        }
                    ],
                    "samples": [
                        "Today {phrase}"
                    ]
                },
                {
                    "name": "AMAZON.YesIntent",
                    "samples": []
                },
                {
                    "name": "AMAZON.NoIntent",
                    "samples": []
                },
                {
                    "name": "AMAZON.NavigateHomeIntent",
                    "samples": []
                }
            ],
            "types": []
        }
    }
}